vae-level-1/sreg_sipo_9x16_bit/sreg_sipo_9x16_bit.v
module sreg_sipo_9x16_bit
    #(parameter N_IN=9,
        parameter WIDTH=16) (
        input clk, rst, load,
        input [WIDTH-1:0] in_serial,
        input [N_IN*WIDTH-1:0] in_parallel, // 9 * 16-bit parallel input (144 bits total)
        output reg [N_IN*WIDTH-1:0] out_parallel // 9 * 16-bit parallel output (144 bits total)
    );

    // Internal register to store 9 16-bit values (144 bits total)
    reg [N_IN*WIDTH-1:0] sreg;    // 9 16-bit registers (144 bits total)

    // Shift register operation
    always @(posedge clk or posedge rst) begin
        if (rst) begin
            sreg <= 144'b0;
            out_parallel <= 144'b0;
        end else if (load) begin
            out_parallel <= sreg;
        end else begin
            sreg <= {sreg[N_IN*WIDTH-WIDTH-1:0], in_serial[WIDTH-1:0]}; // Shift left and load in_serial
        end
    end

endmodule

vae-level-1/sreg_sipo_9x16_bit/tb_sreg_sipo_9x16_bit.v
`include "sreg_sipo_9x16_bit.v"
`timescale 1ps / 1ps

module tb_sreg_sipo_9x16_bit;

    // Testbench signals
    parameter N_IN = 9;
    parameter WIDTH = 16;
    reg clk;
    reg rst;
    reg load;
    reg [WIDTH-1:0] in_serial;
    reg [N_IN*WIDTH-1:0] in_parallel;
    wire [N_IN*WIDTH-1:0] out_parallel;

    // Instantiate the SIPO shift register module
    sreg_sipo_9x16_bit uut (
        .clk(clk),
        .rst(rst),
        .in_serial(in_serial),
        .load(load),
        .out_parallel(out_parallel)
    );

    // Clock generation
    always begin
        #5 clk = ~clk; // Clock period of 10 time units
    end

    // Test procedure
    initial begin
        $dumpfile("tb_sreg_sipo_9x16_bit.vcd");  // VCD file name
        $dumpvars(0, tb_sreg_sipo_9x16_bit);
        // Initialize signals
        clk = 0;
        rst = 1;
        load = 0;
        in_serial = 16'b0;

        #10 rst = 0;

        // Shift in serial data
        #10 in_serial = 16'b1;  // Shift in a bit (1)
        #10 in_serial = 16'b0;  // Shift in a bit (0)
        #10 in_serial = 16'b1;  // Shift in a bit (1)
        #10 in_serial = 16'b0;  // Shift in a bit (0)
        #10 in_serial = 16'b1;  // Shift in a bit (0)
        #10 in_serial = 16'b0;  // Shift in a bit (0)
        #10 in_serial = 16'b0;  // Shift in a bit (0)
        #10 in_serial = 16'b1;  // Shift in a bit (0)
        #10 in_serial = 16'b0;  // Shift in a bit (0)

        #10 load = 1;
        // Finish simulation
        #10 $finish;
    end
endmodule

vae-level-1/sreg_sipo_9x16_bit/tb_sreg_sipo_9x16_bit.vcd
$date
	Mon Dec 02 10:03:36 2024
$end
$version
	Icarus Verilog
$end
$timescale
	1ps
$end
$scope module tb_sreg_sipo_9x16_bit $end
$var wire 144 ! out_parallel [143:0] $end
$var parameter 32 " N_IN $end
$var parameter 32 # WIDTH $end
$var reg 1 $ clk $end
$var reg 16 % in_serial [15:0] $end
$var reg 1 & load $end
$var reg 1 ' rst $end
$scope module uut $end
$var wire 1 $ clk $end
$var wire 144 ( in_parallel [143:0] $end
$var wire 16 ) in_serial [15:0] $end
$var wire 1 & load $end
$var wire 1 ' rst $end
$var parameter 32 * N_IN $end
$var parameter 32 + WIDTH $end
$var reg 144 , out_parallel [143:0] $end
$var reg 144 - sreg [143:0] $end
$upscope $end
$upscope $end
$enddefinitions $end
$comment Show the parameter values. $end
$dumpall
b10000 +
b1001 *
b10000 #
b1001 "
$end
#0
$dumpvars
b0 -
b0 ,
b0 )
bz (
1'
0&
b0 %
0$
b0 !
$end
#5
1$
#10
0$
0'
#15
1$
#20
0$
b1 %
b1 )
#25
b1 -
1$
#30
0$
b0 %
b0 )
#35
b10000000000000000 -
1$
#40
0$
b1 %
b1 )
#45
b100000000000000000000000000000001 -
1$
#50
0$
b0 %
b0 )
#55
b1000000000000000000000000000000010000000000000000 -
1$
#60
0$
b1 %
b1 )
#65
b10000000000000000000000000000000100000000000000000000000000000001 -
1$
#70
0$
b0 %
b0 )
#75
b100000000000000000000000000000001000000000000000000000000000000010000000000000000 -
1$
#80
0$
#85
b1000000000000000000000000000000010000000000000000000000000000000100000000000000000000000000000000 -
1$
#90
0$
b1 %
b1 )
#95
b10000000000000000000000000000000100000000000000000000000000000001000000000000000000000000000000000000000000000001 -
1$
#100
0$
b0 %
b0 )
#105
b100000000000000000000000000000001000000000000000000000000000000010000000000000000000000000000000000000000000000010000000000000000 -
1$
#110
0$
1&
#115
b100000000000000000000000000000001000000000000000000000000000000010000000000000000000000000000000000000000000000010000000000000000 !
b100000000000000000000000000000001000000000000000000000000000000010000000000000000000000000000000000000000000000010000000000000000 ,
1$
