vae-level-1/v2/sqrt/sqrt.v
module sqrt #(
    parameter WIDTH = 16,  // width of radicand
    parameter FBITS = 12   // fractional bits (for fixed point)
) (
    input wire clk,
    input wire start,             // start signal
    output reg busy,              // calculation in progress
    output reg valid,             // root and rem are valid
    input wire [WIDTH-1:0] rad,   // radicand
    output reg [WIDTH-1:0] root,  // root
    output reg [WIDTH-1:0] rem    // remainder
);

    reg [WIDTH-1:0] x, x_next;    // radicand copy
    reg [WIDTH-1:0] q, q_next;    // intermediate root (quotient)
    reg [WIDTH+1:0] ac, ac_next;  // accumulator (2 bits wider)
    reg [WIDTH+1:0] test_res;     // sign test result (2 bits wider)

    localparam ITER = (WIDTH + FBITS) >> 1;  // iterations are half radicand + fbits width
    reg [$clog2(ITER)-1:0] i;            // iteration counter

    always @* begin
        test_res = ac - {q, 2'b01};
        if (test_res[WIDTH+1] == 1'b0) begin  // test_res ≥ 0? (check MSB)
            {ac_next, x_next} = {test_res[WIDTH-1:0], x, 2'b0};
            q_next = {q[WIDTH-2:0], 1'b1};
        end else begin
            {ac_next, x_next} = {ac[WIDTH-1:0], x, 2'b0};
            q_next = q << 1;
        end
    end

    always @(posedge clk) begin
        if (start) begin
            busy <= 1'b1;
            valid <= 1'b0;
            i <= 0;
            q <= 0;
            {ac, x} <= {{WIDTH{1'b0}}, rad, 2'b0};
        end else if (busy) begin
            if (i == ITER - 1) begin  // we're done
                busy <= 1'b0;
                valid <= 1'b1;
                root <= q_next;
                rem <= ac_next[WIDTH+1:2];  // undo final shift
            end else begin  // next iteration
                i <= i + 1;
                x <= x_next;
                ac <= ac_next;
                q <= q_next;
            end
        end
    end
endmodule

vae-level-1/v2/sqrt/sqrt_tb.v
`timescale 1ns/1ps
`include "sqrt.v"

module sqrt_tb();

    parameter CLK_PERIOD = 10;
    parameter WIDTH = 16;
    parameter FBITS = 8;
    parameter SF = 2.0**-8.0;  // Q8.8 scaling factor is 2^-8

    reg clk;
    reg start;              // start signal
    wire busy;              // calculation in progress
    wire valid;             // root and rem are valid
    reg [WIDTH-1:0] rad;    // radicand
    wire [WIDTH-1:0] root;  // root
    wire [WIDTH-1:0] rem;   // remainder

    // Intermediate variables for monitoring
    real rad_real;
    real root_real;

    sqrt #(.WIDTH(WIDTH), .FBITS(FBITS)) sqrt_inst (
        .clk(clk),
        .start(start),
        .busy(busy),
        .valid(valid),
        .rad(rad),
        .root(root),
        .rem(rem)
    );

    always #(CLK_PERIOD / 2) clk = ~clk;

    // Continuous assignments for monitoring
    always @(*) begin
        rad_real = rad * SF;
        root_real = root * SF;
    end

    initial begin
        $dumpfile("sqrt_tb.vcd");
        $dumpvars(0, sqrt_tb);

        $monitor("\t%d:\tsqrt(%f) = %b (%f) (rem = %b) (V=%b)",
                    $time, rad_real, root, root_real, rem, valid);
    end

    initial begin
        clk = 1;
        start = 0;

        #100    rad = 16'b1110_1000_1001_0000;  // 232.56250000
                start = 1;
        #10     start = 0;

        #120    rad = 16'b0000_0000_0100_0000;  // 0.25
                start = 1;
        #10     start = 0;

        #120    rad = 16'b0000_0010_0000_0000;  // 2.0
                start = 1;
        #10     start = 0;

        #120    $finish;
    end
endmodule

vae-level-1/v2/sqrt/sqrt_tb.vcd
$date
	Mon Dec 09 21:01:26 2024
$end
$version
	Icarus Verilog
$end
$timescale
	1ps
$end
$scope module sqrt_tb $end
$var wire 1 ! valid $end
$var wire 16 " root [15:0] $end
$var wire 16 # rem [15:0] $end
$var wire 1 $ busy $end
$var parameter 32 % CLK_PERIOD $end
$var parameter 32 & FBITS $end
$var real 1 ' SF $end
$var parameter 32 ( WIDTH $end
$var reg 1 ) clk $end
$var reg 16 * rad [15:0] $end
$var reg 1 + start $end
$var real 1 , rad_real $end
$var real 1 - root_real $end
$scope module sqrt_inst $end
$var wire 1 ) clk $end
$var wire 16 . rad [15:0] $end
$var wire 1 + start $end
$var parameter 32 / FBITS $end
$var parameter 32 0 ITER $end
$var parameter 32 1 WIDTH $end
$var reg 18 2 ac [17:0] $end
$var reg 18 3 ac_next [17:0] $end
$var reg 1 $ busy $end
$var reg 4 4 i [3:0] $end
$var reg 16 5 q [15:0] $end
$var reg 16 6 q_next [15:0] $end
$var reg 16 7 rem [15:0] $end
$var reg 16 8 root [15:0] $end
$var reg 18 9 test_res [17:0] $end
$var reg 1 ! valid $end
$var reg 16 : x [15:0] $end
$var reg 16 ; x_next [15:0] $end
$upscope $end
$upscope $end
$enddefinitions $end
$comment Show the parameter values. $end
$dumpall
b10000 1
b1100 0
b1000 /
b10000 (
r0.00390625 '
b1000 &
b1010 %
$end
#0
$dumpvars
bx ;
bx :
bx 9
bx 8
bx 7
bx 6
bx 5
bx 4
bx 3
bx 2
bx .
r0 -
r0 ,
0+
bx *
1)
x$
bx #
bx "
x!
$end
#5000
0)
#10000
1)
#15000
0)
#20000
1)
#25000
0)
#30000
1)
#35000
0)
#40000
1)
#45000
0)
#50000
1)
#55000
0)
#60000
1)
#65000
0)
#70000
1)
#75000
0)
#80000
1)
#85000
0)
#90000
1)
#95000
0)
#100000
b1 6
b1010 3
b1000100100000000 ;
b10 9
b11 2
b1010001001000000 :
b0 5
b0 4
0!
1$
r232.5625 ,
1)
1+
b1110100010010000 *
b1110100010010000 .
#105000
0)
#110000
b11 6
b10110 3
b10010000000000 ;
b101 9
b1 5
b1010 2
b1000100100000000 :
b1 4
1)
0+
#115000
0)
#120000
b111 6
b100100 3
b1001000000000000 ;
b1001 9
b11 5
b10110 2
b10010000000000 :
b10 4
1)
#125000
0)
#130000
b1111 6
b11110 3
b100000000000000 ;
b111 9
b111 5
b100100 2
b1001000000000000 :
b11 4
1)
#135000
0)
#140000
b11110 6
b1111001 3
b0 ;
b111111111111100001 9
b1111 5
b11110 2
b100000000000000 :
b100 4
1)
#145000
0)
#150000
b111101 6
b0 3
b0 9
b11110 5
b1111001 2
b0 :
b101 4
1)
#155000
0)
#160000
b1111010 6
b111111111100001011 9
b111101 5
b0 2
b110 4
1)
#165000
0)
#170000
b11110100 6
b111111111000010111 9
b1111010 5
b111 4
1)
#175000
0)
#180000
b111101000 6
b111111110000101111 9
b11110100 5
b1000 4
1)
#185000
0)
#190000
b1111010000 6
b111111100001011111 9
b111101000 5
b1001 4
1)
#195000
0)
#200000
b11110100000 6
b111111000010111111 9
b1111010000 5
b1010 4
1)
#205000
0)
#210000
b111101000000 6
b111110000101111111 9
b11110100000 5
b1011 4
1)
#215000
0)
#220000
r15.25 -
b0 #
b0 7
b111101000000 "
b111101000000 8
1!
0$
1)
#225000
0)
#230000
b0 6
b10000000000 ;
b111111111111111111 9
b100000000 :
b0 5
b0 4
0!
1$
r0.25 ,
1)
1+
b1000000 *
b1000000 .
#235000
0)
#240000
b1000000000000 ;
b10000000000 :
b1 4
1)
0+
#245000
0)
#250000
b100000000000000 ;
b1000000000000 :
b10 4
1)
#255000
0)
#260000
b1 3
b0 ;
b100000000000000 :
b11 4
1)
#265000
0)
#270000
b1 6
b0 3
b0 9
b1 2
b0 :
b100 4
1)
#275000
0)
#280000
b10 6
b111111111111111011 9
b1 5
b0 2
b101 4
1)
#285000
0)
#290000
b100 6
b111111111111110111 9
b10 5
b110 4
1)
#295000
0)
#300000
b1000 6
b111111111111101111 9
b100 5
b111 4
1)
#305000
0)
#310000
b10000 6
b111111111111011111 9
b1000 5
b1000 4
1)
#315000
0)
#320000
b100000 6
b111111111110111111 9
b10000 5
b1001 4
1)
#325000
0)
#330000
b1000000 6
b111111111101111111 9
b100000 5
b1010 4
1)
#335000
0)
#340000
b10000000 6
b111111111011111111 9
b1000000 5
b1011 4
1)
#345000
0)
#350000
r0.5 -
b10000000 "
b10000000 8
1!
0$
1)
#355000
0)
#360000
b0 6
b10000000000000 ;
b111111111111111111 9
b100000000000 :
b0 5
b0 4
0!
1$
r2 ,
1)
1+
b1000000000 *
b1000000000 .
#365000
0)
#370000
b1000000000000000 ;
b10000000000000 :
b1 4
1)
0+
#375000
0)
#380000
b10 3
b0 ;
b1000000000000000 :
b10 4
1)
#385000
0)
#390000
b1 6
b100 3
b1 9
b10 2
b0 :
b11 4
1)
#395000
0)
#400000
b10 6
b10000 3
b111111111111111111 9
b1 5
b100 2
b100 4
1)
#405000
0)
#410000
b101 6
b11100 3
b111 9
b10 5
b10000 2
b101 4
1)
#415000
0)
#420000
b1011 6
b101 5
b11100 2
b110 4
1)
#425000
0)
#430000
b10110 6
b1110000 3
b111111111111101111 9
b1011 5
b111 4
1)
#435000
0)
#440000
b101101 6
b1011100 3
b10111 9
b10110 5
b1110000 2
b1000 4
1)
#445000
0)
#450000
b1011010 6
b101110000 3
b111111111110100111 9
b101101 5
b1011100 2
b1001 4
1)
#455000
0)
#460000
b10110101 6
b11100 3
b111 9
b1011010 5
b101110000 2
b1010 4
1)
#465000
0)
#470000
b101101010 6
b1110000 3
b111111110101000111 9
b10110101 5
b11100 2
b1011 4
1)
#475000
0)
#480000
r1.4140625 -
b11100 #
b11100 7
b101101010 "
b101101010 8
1!
0$
1)
